ab_core/identity_context/__init__.py
ab_core/identity_context/dependency.py
ab_core/identity_context/exceptions.py
ab_core/identity_context/identify.py
ab_core/identity_context/models.py
ab_identity_context-0.2.0.dist-info/METADATA
ab_identity_context-0.2.0.dist-info/WHEEL
ab_identity_context-0.2.0.dist-info/licenses/LICENSE
ab_identity_context-0.2.0.dist-info/RECORD
