Metadata-Version: 2.4
Name: ab-identity-context
Version: 0.2.0
Summary: Glue token validation + user service to provide identity context in FastAPI
Author-email: Matt Coulter <mattcoul7@gmail.com>
License-File: LICENSE
Requires-Python: <4.0,>=3.12
Requires-Dist: ab-client-token-validator<2,>=1.1.1
Requires-Dist: ab-client-user<2,>=1.1.1
Requires-Dist: ab-dependency<0.3.0,>=0.2.0
Requires-Dist: pydantic>=2.11.10
Provides-Extra: all
Requires-Dist: fastapi>=0.115.14; extra == 'all'
Provides-Extra: fastapi
Requires-Dist: fastapi>=0.115.14; extra == 'fastapi'
